mdcor/__init__.py
mdcor/cli.py
mdcor/converts.py
mdcor/process_yalm.py
mdcor/watcher.py
mdcor-0.1.0.dist-info/LICENSE
mdcor-0.1.0.dist-info/METADATA
mdcor-0.1.0.dist-info/WHEEL
mdcor-0.1.0.dist-info/entry_points.txt
mdcor-0.1.0.dist-info/RECORD
