Metadata-Version: 2.1
Name: mdcor
Version: 0.1.0
Summary: 
Author: infocornouaille
Author-email: 90894019+infocornouaille@users.noreply.github.com
Requires-Python: >=3.9,<4.0
Classifier: Programming Language :: Python :: 3
Classifier: Programming Language :: Python :: 3.9
Classifier: Programming Language :: Python :: 3.10
Classifier: Programming Language :: Python :: 3.11
Classifier: Programming Language :: Python :: 3.12
Requires-Dist: imagecor (>=0.1.0,<0.2.0)
Requires-Dist: pypandoc (>=1.14,<2.0)
Requires-Dist: pyyaml (>=6.0.2,<7.0.0)
Requires-Dist: watchdog (>=5.0.3,<6.0.0)
